{".class": "MypyFile", "_fullname": "six.moves.configparser", "is_partial_stub_package": false, "is_stub": true, "names": {".class": "SymbolTable", "ConfigParser": {".class": "SymbolTableNode", "cross_ref": "ConfigParser.ConfigParser", "kind": "Gdef"}, "DEFAULTSECT": {".class": "SymbolTableNode", "cross_ref": "ConfigParser.DEFAULTSECT", "kind": "Gdef"}, "DuplicateSectionError": {".class": "SymbolTableNode", "cross_ref": "ConfigParser.DuplicateSectionError", "kind": "Gdef"}, "Error": {".class": "SymbolTableNode", "cross_ref": "ConfigParser.Error", "kind": "Gdef"}, "InterpolationDepthError": {".class": "SymbolTableNode", "cross_ref": "ConfigParser.InterpolationDepthError", "kind": "Gdef"}, "InterpolationError": {".class": "SymbolTableNode", "cross_ref": "ConfigParser.InterpolationError", "kind": "Gdef"}, "InterpolationMissingOptionError": {".class": "SymbolTableNode", "cross_ref": "ConfigParser.InterpolationMissingOptionError", "kind": "Gdef"}, "InterpolationSyntaxError": {".class": "SymbolTableNode", "cross_ref": "ConfigParser.InterpolationSyntaxError", "kind": "Gdef"}, "MAX_INTERPOLATION_DEPTH": {".class": "SymbolTableNode", "cross_ref": "ConfigParser.MAX_INTERPOLATION_DEPTH", "kind": "Gdef"}, "MissingSectionHeaderError": {".class": "SymbolTableNode", "cross_ref": "ConfigParser.MissingSectionHeaderError", "kind": "Gdef"}, "NoOptionError": {".class": "SymbolTableNode", "cross_ref": "ConfigParser.NoOptionError", "kind": "Gdef"}, "NoSectionError": {".class": "SymbolTableNode", "cross_ref": "ConfigParser.NoSectionError", "kind": "Gdef"}, "ParsingError": {".class": "SymbolTableNode", "cross_ref": "ConfigParser.ParsingError", "kind": "Gdef"}, "RawConfigParser": {".class": "SymbolTableNode", "cross_ref": "ConfigParser.RawConfigParser", "kind": "Gdef"}, "SafeConfigParser": {".class": "SymbolTableNode", "cross_ref": "ConfigParser.SafeConfigParser", "kind": "Gdef"}, "__doc__": {".class": "SymbolTableNode", "kind": "Gdef", "node": {".class": "Var", "flags": ["is_ready"], "fullname": "six.moves.configparser.__doc__", "name": "__doc__", "type": {".class": "UnionType", "items": ["builtins.str", "builtins.unicode"]}}}, "__file__": {".class": "SymbolTableNode", "kind": "Gdef", "node": {".class": "Var", "flags": ["is_ready"], "fullname": "six.moves.configparser.__file__", "name": "__file__", "type": "builtins.str"}}, "__name__": {".class": "SymbolTableNode", "kind": "Gdef", "node": {".class": "Var", "flags": ["is_ready"], "fullname": "six.moves.configparser.__name__", "name": "__name__", "type": "builtins.str"}}, "__package__": {".class": "SymbolTableNode", "kind": "Gdef", "node": {".class": "Var", "flags": ["is_ready"], "fullname": "six.moves.configparser.__package__", "name": "__package__", "type": "builtins.str"}}}, "path": "/usr/local/lib/python3.7/site-packages/mypy/typeshed/third_party/2/six/moves/configparser.pyi"}